odoo/addons/sale_order_line_serial_unique/README.rst
odoo/addons/sale_order_line_serial_unique/__init__.py
odoo/addons/sale_order_line_serial_unique/__manifest__.py
odoo/addons/sale_order_line_serial_unique/i18n/sale_order_line_serial_unique.pot
odoo/addons/sale_order_line_serial_unique/models/__init__.py
odoo/addons/sale_order_line_serial_unique/models/sale_order_line.py
odoo/addons/sale_order_line_serial_unique/readme/CONTRIBUTORS.rst
odoo/addons/sale_order_line_serial_unique/readme/DESCRIPTION.rst
odoo/addons/sale_order_line_serial_unique/static/description/icon.png
odoo/addons/sale_order_line_serial_unique/static/description/index.html
odoo/addons/sale_order_line_serial_unique/tests/__init__.py
odoo/addons/sale_order_line_serial_unique/tests/test_serial_unique.py
odoo12_addon_sale_order_line_serial_unique-12.0.1.0.0.99.dev2.dist-info/METADATA
odoo12_addon_sale_order_line_serial_unique-12.0.1.0.0.99.dev2.dist-info/WHEEL
odoo12_addon_sale_order_line_serial_unique-12.0.1.0.0.99.dev2.dist-info/top_level.txt
odoo12_addon_sale_order_line_serial_unique-12.0.1.0.0.99.dev2.dist-info/RECORD
